[
  {
    "title": "Caesar Encryption",
    "path": "Cesar_encryption",
    "main_file": "cesar.py",
    "summary": "A simple Caesar cipher example that shifts alphabetic text while keeping punctuation unchanged.",
    "details": [
      "Supports both uppercase and lowercase letters.",
      "Uses modulo arithmetic to wrap around the alphabet cleanly.",
      "Includes a small example that encrypts the word 'mohamed' with a shift of 3."
    ],
    "requirements": [
      "Python 3"
    ]
  },
  {
    "title": "Random Word Game",
    "path": "Random Word game",
    "main_file": "RandomWordGame.py",
    "summary": "A console word guessing game inspired by Hangman.",
    "details": [
      "Chooses a random word from a small built-in word bank.",
      "Shows progress after every guess and tracks remaining attempts.",
      "Ends with either a victory message or the correct answer when attempts run out."
    ],
    "requirements": [
      "Python 3"
    ]
  },
  {
    "title": "Search Engine",
    "path": "Search Engine",
    "main_file": "ExaEngine.py",
    "summary": "A command-line search example built with the Exa API.",
    "details": [
      "Prompts the user for a search query.",
      "Fetches up to five keyword-based search results.",
      "Currently filters results to the Netflix domain as a focused demo."
    ],
    "requirements": [
      "Python 3",
      "exa-py",
      "An Exa API key"
    ]
  },
  {
    "title": "Discord Chatbot",
    "path": "discord_chatbot",
    "main_file": "discord vhatbot.py",
    "summary": "A starter Discord bot configured with a command prefix and message intents.",
    "details": [
      "Creates a bot with the '!' command prefix.",
      "Enables basic message intents so the bot can respond to server activity.",
      "Provides a minimal foundation for adding commands and events."
    ],
    "requirements": [
      "Python 3",
      "discord.py",
      "A Discord bot token"
    ]
  },
  {
    "title": "YouTube Video Downloader",
    "path": "youtube_video_downloader",
    "main_file": "YT.py",
    "summary": "A utility that downloads a YouTube video with yt-dlp.",
    "details": [
      "Accepts a YouTube URL and an optional output folder.",
      "Downloads the best video stream up to 1080p and shows progress updates.",
      "Prints the saved file path after the download finishes."
    ],
    "requirements": [
      "Python 3",
      "yt-dlp"
    ]
  }
]
